frequency_max_power/__init__.py
frequency_max_power/frequency_max_power.py
frequency_max_power-0.1.1.dist-info/METADATA
frequency_max_power-0.1.1.dist-info/WHEEL
frequency_max_power-0.1.1.dist-info/top_level.txt
frequency_max_power-0.1.1.dist-info/RECORD
