Metadata-Version: 2.1
Name: frequency-max-power
Version: 0.1.1
Summary: A Python library for calculating frequency_max_power
Home-page: https://github.com/Metaverse-Crowdsource/EEG-Chaos-Kuramoto-Neural-Net/blob/main/Higuchi_Fractal_Dimension_files/Higuchi%20Fractal%20Dimension.ipynb
Author: soul_syrup
Author-email: soul.syrupp@gmail.com
Requires-Dist: numpy
